newton_clips-0.1.8.dist-info/licenses/LICENSE
newtonclips/__init__.py
newton_clips-0.1.8.dist-info/METADATA
newton_clips-0.1.8.dist-info/WHEEL
newton_clips-0.1.8.dist-info/top_level.txt
newton_clips-0.1.8.dist-info/RECORD
