Metadata-Version: 2.4
Name: newton-clips
Version: 0.1.8
Summary: Clips from newton-physics simulation to Unreal Engine 5 runtime
Project-URL: Homepage, https://github.com/doidio/newton-clips
Project-URL: Repository, https://github.com/doidio/newton-clips
Project-URL: Issues, https://github.com/doidio/newton-clips/issues
Keywords: newton,physics,simulation,unreal engine
Requires-Python: >=3.9
License-File: LICENSE
Requires-Dist: warp-lang
Requires-Dist: newton-physics
Requires-Dist: mujoco-warp
Requires-Dist: scipy>=1.13.1
Requires-Dist: trimesh>=4.7.1
Requires-Dist: networkx>=3.2.1
Requires-Dist: pyglet
Dynamic: license-file
